cloudben/__init__.py
cloudben/__main__.py
cloudben/main.py
cloudben-1.0.0.dist-info/METADATA
cloudben-1.0.0.dist-info/WHEEL
cloudben-1.0.0.dist-info/entry_points.txt
cloudben-1.0.0.dist-info/RECORD
