Metadata-Version: 2.1
Name: cloudben
Version: 1.0.0
Summary: Simple CLI tool to interact with the Cloudflare APIs.
Author: Alberto Gallinaro
Author-email: albertogdesign@gmail.com
Requires-Python: >=3.12,<4.0
Classifier: Programming Language :: Python :: 3
Classifier: Programming Language :: Python :: 3.12
Requires-Dist: requests (>=2.31.0,<3.0.0)
Requires-Dist: typer[all] (>=0.12.3,<0.13.0)
